nodelp/__init__.py
nodelp/modules/__init__.py
nodelp/py.typed
nodelp/routines/__init__.py
nodelp-0.1.8.dist-info/WHEEL
nodelp-0.1.8.dist-info/METADATA
nodelp-0.1.8.dist-info/RECORD
