Metadata-Version: 2.3
Name: nodelp
Version: 0.1.8
Summary: A library that generates various kinds of point clouds and coordinates.
Requires-Dist: corelp
Requires-Python: >=3.12
